gasoptics/__init__.py
gasoptics/backends/K_normal.py
gasoptics/backends/__init__.py
gasoptics/backends/redlich_kwong.py
gasoptics/fluids/air.json
gasoptics/fluids/water_vapor.json
gasoptics/properties/__init__.py
gasoptics/properties/cp.py
gasoptics/properties/cv.py
gasoptics/properties/density.py
gasoptics/properties/enthalpy.py
gasoptics/properties/entropy.py
gasoptics/properties/gamma.py
gasoptics/properties/gas_constant.py
gasoptics/properties/thermal_conductivity.py
gasoptics/properties/viscosity.py
gasoptics/utils/__init__.py
gasoptics/utils/unit_converter.py
gasoptics-0.3.2.dist-info/LICENSE
gasoptics-0.3.2.dist-info/METADATA
gasoptics-0.3.2.dist-info/WHEEL
gasoptics-0.3.2.dist-info/top_level.txt
gasoptics-0.3.2.dist-info/RECORD
