Metadata-Version: 2.1
Name: gasoptics
Version: 0.3.2
Summary: A library for thermodynamic and transport property calculations of gases.
Home-page: https://github.com/karimialii/gasoptics
Author: Ali Karimi
Author-email: karimi1991ali@gmail.com
Classifier: Programming Language :: Python :: 3
Classifier: License :: OSI Approved :: MIT License
Classifier: Operating System :: OS Independent
Classifier: Programming Language :: Python :: 3.6
Classifier: Programming Language :: Python :: 3.7
Classifier: Programming Language :: Python :: 3.8
Classifier: Programming Language :: Python :: 3.9
Requires-Python: >=3.6
License-File: LICENSE
Requires-Dist: numpy
